grid_samp/__init__.py
grid_samp/image_region.py
grid_samp/image_region_list.py
grid_samp/assemble/__init__.py
grid_samp/assemble/contextualize.py
grid_samp/assemble/image_region_intersection_heatmap.py
grid_samp/assemble/mosaic.py
grid_samp/assemble/roi.py
grid_samp/grids/__init__.py
grid_samp/grids/fixed_grid.py
grid_samp/grids/recursive_grid.py
grid_samp/grids/region_based_grid.py
grid_samp/grids/spaced_grid.py
grid_samp-0.1.3.dist-info/METADATA
grid_samp-0.1.3.dist-info/WHEEL
grid_samp-0.1.3.dist-info/licenses/LICENSE
grid_samp-0.1.3.dist-info/RECORD
