Metadata-Version: 2.4
Name: grid_samp
Version: 0.1.3
Summary: The official PIL Implementation of GridSamp: A common environment for grid-based image sampling using intuitive python code.
Project-URL: Homepage, https://github.com/MLeemans1/GridSamp
Project-URL: Issues, https://github.com/MLeemans1/GridSamp
Author-email: Maarten Leemans <maarten.leemans@kuleuven.be>, Christophe Bossens <christophe.bossens@kuleuven.be>, Johan Wagemans <johan.wagemans@kuleuven.be>
Maintainer-email: Maarten Leemans <maarten.leemans@kuleuven.be>
License:                     GNU GENERAL PUBLIC LICENSE
License-File: LICENSE
Classifier: License :: OSI Approved :: GNU General Public License v3 (GPLv3)
Classifier: Operating System :: OS Independent
Classifier: Programming Language :: Python :: 3
Requires-Python: >=3.8
Requires-Dist: matplotlib>=3.9
Requires-Dist: numpy>=1.25
Requires-Dist: pillow>=10.0
Requires-Dist: scikit-image>=0.23
Requires-Dist: scipy>=1.12
